AutoDifferentiation/DualNumber.py
AutoDifferentiation/Forward.py
AutoDifferentiation/elementary.py
Automatic_Differentiation_CS107_Team50-0.0.1.dist-info/LICENSE
Automatic_Differentiation_CS107_Team50-0.0.1.dist-info/METADATA
Automatic_Differentiation_CS107_Team50-0.0.1.dist-info/WHEEL
Automatic_Differentiation_CS107_Team50-0.0.1.dist-info/top_level.txt
Automatic_Differentiation_CS107_Team50-0.0.1.dist-info/RECORD
